{
  "microservices" :
	[
	  {
      "name" : "Gateway",
      "instances" : 5,
      "power" : 3.5,
      "operations" : 
      [
        {
          "name" : "doStuff",
          "pattern" : "Circuit Breaker",
          "duration" : 4,
          "propability" : 0.8,
          "dependencies" : 
          [
            {"Database" : "save"}
          ]						
        }
      ]
	  }
	],
  "generators" :
	[
	  {
      "time" : 1,
      "microservice" : 0
	  }
	],
  "errormonkeys" :
	[
	  {
      "time" : 10,
      "microservice" : 0,
      "instances" : 5
	  },
	  {
      "time" : 100,
      "microservice" : 2,
      "instances" : 1
	  }
	]
}